tonnikala/__init__.py
tonnikala/exceptions.py
tonnikala/expr.py
tonnikala/loader.py
tonnikala/helpers/__init__.py
tonnikala/i18n/__init__.py
tonnikala/ir/__init__.py
tonnikala/ir/generate.py
tonnikala/ir/nodes.py
tonnikala/languages/__init__.py
tonnikala/languages/base.py
tonnikala/languages/javascript/__init__.py
tonnikala/languages/javascript/generator.py
tonnikala/languages/javascript/jslex.py
tonnikala/languages/python/__init__.py
tonnikala/languages/python/astalyzer.py
tonnikala/languages/python/generator.py
tonnikala/pyramid/__init__.py
tonnikala/runtime/__init__.py
tonnikala/runtime/debug.py
tonnikala/runtime/exceptions.py
tonnikala/runtime/javascript.js
tonnikala/runtime/python.py
tonnikala/syntaxes/__init__.py
tonnikala/syntaxes/chameleon.py
tonnikala/syntaxes/docparser.py
tonnikala/syntaxes/tonnikala.py
tonnikala-1.0.0.data/scripts/tonnikala-compile-jstemplate
tonnikala-1.0.0.dist-info/licenses/LICENSE.txt
tonnikala-1.0.0.dist-info/METADATA
tonnikala-1.0.0.dist-info/WHEEL
tonnikala-1.0.0.dist-info/entry_points.txt
tonnikala-1.0.0.dist-info/top_level.txt
tonnikala-1.0.0.dist-info/RECORD
