Metadata-Version: 2.1
Name: tonnikala
Version: 1.0.0
Summary: Python templating engine - the one ton solution
Home-page: https://github.com/tetframework/Tonnikala
Author: Antti Haapala
Author-email: antti.haapala@interjektio.fi
Classifier: Development Status :: 4 - Beta
Classifier: Environment :: Web Environment
Classifier: Framework :: Pyramid
Classifier: Intended Audience :: Developers
Classifier: License :: OSI Approved :: Apache Software License
Classifier: Operating System :: OS Independent
Classifier: Programming Language :: Python
Classifier: Programming Language :: Python :: 3.8
Classifier: Programming Language :: Python :: 3.9
Classifier: Programming Language :: Python :: 3.10
Classifier: Programming Language :: Python :: 3.11
Classifier: Programming Language :: Python :: 3.12
Classifier: Programming Language :: Python :: 3.13
Classifier: Programming Language :: Python :: 3.14
Classifier: Programming Language :: Python :: Implementation :: CPython
Classifier: Topic :: Internet :: WWW/HTTP :: Dynamic Content
Classifier: Topic :: Text Processing :: Markup :: HTML
License-File: LICENSE.txt
Requires-Dist: markupsafe >=0.18
Provides-Extra: javascript
Requires-Dist: slimit3k ; extra == 'javascript'
Requires-Dist: ply >=3.4.0 ; extra == 'javascript'
